mermaidz/__init__.py
mermaidz/core.py
mermaidz/templater.py
mermaidz-1.0.1.dist-info/METADATA
mermaidz-1.0.1.dist-info/WHEEL
mermaidz-1.0.1.dist-info/top_level.txt
mermaidz-1.0.1.dist-info/RECORD
