Metadata-Version: 2.4
Name: mermaidz
Version: 1.0.1
Summary: Add your description here
Requires-Python: >=3.10
Requires-Dist: toml>=0.10.2
